tseuler/__init__.py
tseuler/_utils/__init__.py
tseuler/tsmad/__init__.py
tseuler/tsmad/_board.py
tseuler/tsmad/_panelview.py
tseuler/tsmad/_helpers/__init__.py
tseuler/tsmad/_helpers/_htmls.py
tseuler/tsmad/_helpers/_logo.png
tseuler/tsmad/_helpers/_paths.py
tseuler/tsmad/_helpers/_processing_funcs.py
tseuler/tsmad/_helpers/_static.py
tseuler/tsmad/_plottting/__init__.py
tseuler/tsmad/_plottting/_bivariate_plots.py
tseuler/tsmad/_plottting/_plotting_handler.py
tseuler/tsmad/_plottting/_trivariate_plots.py
tseuler/tsmad/_plottting/_univariate_plots.py
tseuler/tsmad/_slabviews/_S1_slab.py
tseuler/tsmad/_slabviews/_S2_slab.py
tseuler/tsmad/_slabviews/_S3_slab.py
tseuler/tsmad/_slabviews/__init__.py
tseuler/tsstats/__init__.py
tseuler/tsstats/_entropy_functions.py
tseuler/tsstats/_modelling_frameworks.py
tseuler/tsstats/_residual_diagnostics.py
tseuler/tsstats/_statistical_tests.py
tseuler-0.0.4.dev0.dist-info/LICENSE
tseuler-0.0.4.dev0.dist-info/METADATA
tseuler-0.0.4.dev0.dist-info/WHEEL
tseuler-0.0.4.dev0.dist-info/top_level.txt
tseuler-0.0.4.dev0.dist-info/RECORD
