Metadata-Version: 2.1
Name: tseuler
Version: 0.0.4.dev0
Summary: A library for Time-Series exploration, analysis & modelling.
Home-page: https://github.com/ag-ds-bubble/tseuler
Author: Achintya Gupta
Author-email: ag.ds.bubble@gmail.com
License: UNKNOWN
Platform: UNKNOWN
Classifier: Programming Language :: Python :: 3
Classifier: Development Status :: 4 - Beta
Classifier: Intended Audience :: Developers
Classifier: License :: OSI Approved :: BSD License
Classifier: Operating System :: OS Independent
Requires-Python: >=3.7
Requires-Dist: matplotlib (>=3.2.2)
Requires-Dist: altair (>=4.1.0)
Requires-Dist: tqdm (>=4.52.0)
Requires-Dist: param (>=1.10.0)
Requires-Dist: numpy (>=1.19.4)
Requires-Dist: mplfinance (>=0.12.7a0)
Requires-Dist: bokeh (>=2.2.3)
Requires-Dist: seaborn (>=0.11.0)
Requires-Dist: statsmodels (>=0.12.1)
Requires-Dist: pandas (>=1.1.4)
Requires-Dist: panel (>=0.10.1)
Requires-Dist: ipython (>=7.19.0)
